{"name":"shouldBeAbleToLogin","id":"com.gmail.tests.features.search.WhenLoginToGmail:shouldBeAbleToLogin","testCaseName":"com.gmail.tests.features.search.WhenLoginToGmail","testSteps":[{"number":1,"description":"On google page","duration":12115,"startTime":"2018-02-18T20:50:52.891+05:30[Asia/Calcutta]","screenshots":[{"screenshot":"aa5e67aeb597bf85241647fe129cc1b19355fd2286faa5c4253335910cfe8f73.png"}],"result":"SUCCESS","precondition":false},{"number":2,"description":"Click gmail","duration":4711,"startTime":"2018-02-18T20:51:05.026+05:30[Asia/Calcutta]","screenshots":[{"screenshot":"5cc375df85762304945de5ad04f31e904e09805dd7b8e600f58f42fe6d9e356a.png"},{"screenshot":"4ae2fb1e3747d844130a078b42ea6ccd632b69cd56a2b888ff91bd05ac5b22bf.png"}],"result":"SUCCESS","precondition":false}],"userStory":{"id":"com.gmail.tests.features.search.WhenLoginToGmail","storyName":"When login to gmail","storyClassName":"com.gmail.tests.features.search.WhenLoginToGmail","path":"com.gmail.tests.features.search","type":"story"},"featureTag":{"name":"Search/When login to gmail","type":"story"},"title":"Should be able to login","tags":[{"name":"Search/When login to gmail","type":"story"}],"startTime":"2018-02-18T20:50:51.583+05:30[Asia/Calcutta]","duration":18208,"testFailureCause":{"errorType":"java.lang.NullPointerException","stackTrace":[{"declaringClass":"com.gmail.tests.features.search.WhenLoginToGmail","methodName":"shouldBeAbleToLogin","fileName":"WhenLoginToGmail.java","lineNumber":31}]},"testFailureClassname":"java.lang.NullPointerException","testFailureSummary":"ERROR;java.lang.NullPointerException;null;WhenLoginToGmail.java","projectKey":"","annotatedResult":"ERROR","sessionId":"e064b60c089639b6d46583da47946174","driver":"chrome","manual":false,"testSource":"JUnit","result":"ERROR"}